qwen_webapi/__init__.py
qwen_webapi/api.py
qwen_webapi/core.py
qwen_webapi/server.py
qwen_webapi/utils.py
qwen_webapi/oss/__init__.py
qwen_webapi/oss/sign.py
qwen_webapi/oss/types.py
qwen_webapi-0.1.2.dist-info/METADATA
qwen_webapi-0.1.2.dist-info/WHEEL
qwen_webapi-0.1.2.dist-info/top_level.txt
qwen_webapi-0.1.2.dist-info/RECORD
