Metadata-Version: 2.4
Name: qwen-webapi
Version: 0.1.2
Summary: OpenAI-compatible API proxy for chat.qwen.ai with Flask server and Python API
Author: Starreeze
License: GPL-3.0-only
Keywords: qwen,api,proxy,openai,chat,llm
Classifier: Development Status :: 3 - Alpha
Classifier: Intended Audience :: Developers
Classifier: License :: OSI Approved :: GNU General Public License v3 (GPLv3)
Classifier: Programming Language :: Python :: 3
Classifier: Topic :: Software Development :: Libraries :: Python Modules
Classifier: Topic :: Scientific/Engineering :: Artificial Intelligence
Requires-Python: >=3.10
Requires-Dist: flask>=2.0.0
Requires-Dist: flask-cors>=3.0.0
Requires-Dist: requests>=2.25.0
